{
    "$schema": "https://schema.management.azure.com/schemas/2015-01-01/deploymentTemplate.json#",
    "contentVersion": "1.0.0.1",
    "parameters": {
      "asgName": {
        "type": "string"
      },
      "asgNames": { 
      },
      "customTages": {
        "type": "object"
      }
    },
    "variables": {
      "location": "[resourceGroup().location]" 
        
    },
    "resources": [
      {
        "name": "[parameters('asgName')]",
        "type": "Microsoft.Network/applicationSecurityGroups",
        "apiVersion": "2018-08-01",
        "dependsOn": [],
        "tags": "[parameters('customTages')]",
        "location": "[variables('location')]",
        "properties": {}  
      },
      {
        "name": "[parameters('asgNames')[copyIndex()]]",
        "copy" : {
          "name": "asgGroups",
          "count": "[length(parameters('asgNames'))]",
          "type": "Microsoft.Network/applicationSecurityGroups",
          "apiVersion": "2018-08-01",
          "dependsOn": [],
          "tags": "[parameters('customTages')]",
          "location": "[variables('location')]",
          "properties": {}  
        }
      }
      
    ],
    "outputs": {
    }
}
  